[ {
  "Command" : "1",
  "Hit" : "+8",
  "Block" : "+1",
  "Notes" : "C \n",
  "Name" : "Sengeki",
  "Total" : "",
  "Counter Hit" : "+8",
  "Property" : "H",
  "Damage" : "7",
  "Startup" : "10F"
}, {
  "Command" : "1, 1+2",
  "Hit" : "+22",
  "Block" : "+15",
  "Notes" : "Super Combo Gauge Cost 1\nBlock -3F/Hit +4F after Forcus Attack to canncel",
  "Name" : "Sengeki to Focus Attack",
  "Total" : "",
  "Counter Hit" : "+22",
  "Property" : "H,SP",
  "Damage" : "7",
  "Startup" : ""
}, {
  "Command" : "1, 1",
  "Hit" : "+4",
  "Block" : "-3",
  "Notes" : "C \nCombo from 1st CH",
  "Name" : "Kimon Rendan",
  "Total" : "",
  "Counter Hit" : "+4",
  "Property" : "H,H",
  "Damage" : "7,7",
  "Startup" : ""
}, {
  "Command" : "1, 1, 1+2",
  "Hit" : "+22",
  "Block" : "+15",
  "Notes" : "Super Combo Gauge Cost 1\nBlock -3F/Hit +4F after Forcus Attack to canncel",
  "Name" : "Kimon Rendan to Focus Attack",
  "Total" : "",
  "Counter Hit" : "+22",
  "Property" : "H,H,SP",
  "Damage" : "7,7",
  "Startup" : ""
}, {
  "Command" : "1, 2",
  "Hit" : "KDN",
  "Block" : "-17",
  "Notes" : "Combo from 1st NH",
  "Name" : "Kimon Rentotsu",
  "Total" : "",
  "Counter Hit" : "KDN",
  "Property" : "H,M",
  "Damage" : "7,20",
  "Startup" : ""
}, {
  "Command" : "2",
  "Hit" : "±0",
  "Block" : "-9",
  "Notes" : "C ",
  "Name" : "Roppu Tubushi",
  "Total" : "",
  "Counter Hit" : "±0",
  "Property" : "SM",
  "Damage" : "15",
  "Startup" : "15F"
}, {
  "Command" : "2, 1+2",
  "Hit" : "+28",
  "Block" : "+19",
  "Notes" : "Super Combo Gauge Cost 1\nBlock +1F/Hit +10F after Forcus Attack to canncel",
  "Name" : "Roppu Tubushi to Focus Attack",
  "Total" : "",
  "Counter Hit" : "+28",
  "Property" : "SM,SP",
  "Damage" : "15",
  "Startup" : ""
}, {
  "Command" : "3",
  "Hit" : "+3",
  "Block" : "-8",
  "Notes" : "",
  "Name" : "Side High Kick",
  "Total" : "",
  "Counter Hit" : "+3",
  "Property" : "H",
  "Damage" : "14",
  "Startup" : "15F"
}, {
  "Command" : "4",
  "Hit" : "+2",
  "Block" : "-13",
  "Notes" : "",
  "Name" : "High Kick",
  "Total" : "",
  "Counter Hit" : "+2",
  "Property" : "H",
  "Damage" : "12",
  "Startup" : "14F"
}, {
  "Command" : "4, 3",
  "Hit" : "+19Sp",
  "Block" : "-5",
  "Notes" : "H TS \nCombo from 1st NH",
  "Name" : "Kikoku Renzan",
  "Total" : "",
  "Counter Hit" : "KDN",
  "Property" : "H,H",
  "Damage" : "12,17",
  "Startup" : ""
}, {
  "Command" : "f3",
  "Hit" : "+7",
  "Block" : "-4",
  "Notes" : "",
  "Name" : "Ryujinkyaku",
  "Total" : "",
  "Counter Hit" : "+7",
  "Property" : "M",
  "Damage" : "16",
  "Startup" : "17F"
}, {
  "Command" : "f4",
  "Hit" : "KDN",
  "Block" : "-5",
  "Notes" : "H TS \nMeaty 1F in actualy\n",
  "Name" : "Onikubigari",
  "Total" : "41",
  "Counter Hit" : "KDN*",
  "Property" : "H",
  "Damage" : "20",
  "Startup" : "16F"
}, {
  "Command" : "f1+2",
  "Hit" : "+7C",
  "Block" : "-8C",
  "Notes" : "Block or Hit force to crouching\n",
  "Name" : "Zugaihasatsu",
  "Total" : "",
  "Counter Hit" : "+7C",
  "Property" : "MM",
  "Damage" : "8,17",
  "Startup" : "20F"
}, {
  "Command" : "f3+4",
  "Hit" : "+2",
  "Block" : "-9",
  "Notes" : "H TJ 9F",
  "Name" : "Hisenkyaku",
  "Total" : "",
  "Counter Hit" : "+2",
  "Property" : "M",
  "Damage" : "20",
  "Startup" : "22F"
}, {
  "Command" : "df1",
  "Hit" : "+7",
  "Block" : "-4",
  "Notes" : "",
  "Name" : "Gokumonsyo (1)",
  "Total" : "",
  "Counter Hit" : "+7",
  "Property" : "M",
  "Damage" : "10",
  "Startup" : "13F"
}, {
  "Command" : "df1, 1",
  "Hit" : "+6",
  "Block" : "-3",
  "Notes" : "Combo from 1st NH",
  "Name" : "Gokumonsyo",
  "Total" : "",
  "Counter Hit" : "+6",
  "Property" : "M,H",
  "Damage" : "10,7",
  "Startup" : ""
}, {
  "Command" : "df1, 2",
  "Hit" : "+7C",
  "Block" : "-13C",
  "Notes" : "Combo from 1st NH\nBlock or Hit force to crouching\n",
  "Name" : "Zugaigohasatsu",
  "Total" : "",
  "Counter Hit" : "+7C",
  "Property" : "M,MM",
  "Damage" : "10,5,15",
  "Startup" : ""
}, {
  "Command" : "df2",
  "Hit" : "+3",
  "Block" : "-7",
  "Notes" : "",
  "Name" : "Dohatsu Tensho (1)",
  "Total" : "",
  "Counter Hit" : "+3",
  "Property" : "M",
  "Damage" : "10",
  "Startup" : "16F"
}, {
  "Command" : "df2, 1",
  "Hit" : "LNC",
  "Block" : "-18",
  "Notes" : "Combo from 1st NH\nCan be delayed 5F\nCombo can be delayed 5F from 1st NH",
  "Name" : "Dohatsu Tensho",
  "Total" : "",
  "Counter Hit" : "LNC",
  "Property" : "M,M",
  "Damage" : "10,10",
  "Startup" : ""
}, {
  "Command" : "df2, 4",
  "Hit" : "±0",
  "Block" : "-11",
  "Notes" : "Combo from 1st NH",
  "Name" : "Gokusatsu Gotenshu (2)",
  "Total" : "",
  "Counter Hit" : "±0",
  "Property" : "M,M",
  "Damage" : "10,13",
  "Startup" : ""
}, {
  "Command" : "df2, 4, 3",
  "Hit" : "KDN",
  "Block" : "-17",
  "Notes" : "Combo from 2nd CH\nCan be delayed 13F\nCombo can be delayed 11F from 2nd CH",
  "Name" : "Gokusatsu Gotenshu",
  "Total" : "",
  "Counter Hit" : "KDN",
  "Property" : "M,M,M",
  "Damage" : "10,13,23",
  "Startup" : ""
}, {
  "Command" : "df3",
  "Hit" : "+1",
  "Block" : "-9",
  "Notes" : "",
  "Name" : "Yokogeri",
  "Total" : "",
  "Counter Hit" : "+1",
  "Property" : "M",
  "Damage" : "14",
  "Startup" : "12F"
}, {
  "Command" : "df4",
  "Hit" : "KDN",
  "Block" : "-16",
  "Notes" : "",
  "Name" : "Kitotsukyaku",
  "Total" : "",
  "Counter Hit" : "KDN",
  "Property" : "M",
  "Damage" : "24",
  "Startup" : "19F"
}, {
  "Command" : "df1+2",
  "Hit" : "KDN",
  "Block" : "-14",
  "Notes" : "PC 8F\n",
  "Name" : "Gokumonkai",
  "Total" : "",
  "Counter Hit" : "KDN",
  "Property" : "M",
  "Damage" : "23",
  "Startup" : "20F"
}, {
  "Command" : "dbor d1or FC 1",
  "Hit" : "+6",
  "Block" : "-5",
  "Notes" : "TC 4FC \nReturns to crouching.\nInput<img src=\"../6'.bmp\" class=\"c\">to standing",
  "Name" : "Fukusengeki",
  "Total" : "",
  "Counter Hit" : "+6",
  "Property" : "SM",
  "Damage" : "5",
  "Startup" : "10F"
}, {
  "Command" : "dbor d1or FC 1, 1+2",
  "Hit" : "+27",
  "Block" : "+16",
  "Notes" : "TC 4F\nSuper Combo Gauge Cost 1\nBlock -2F/Hit +9F after Forcus Attack to canncel",
  "Name" : "Fukusengeki to Focus Attack",
  "Total" : "",
  "Counter Hit" : "+27",
  "Property" : "SM,SP",
  "Damage" : "5",
  "Startup" : ""
}, {
  "Command" : "dbor d1, 2or FC 1, 2",
  "Hit" : "-2",
  "Block" : "-13",
  "Notes" : "TC C \nReturns to crouching.\nCombo from 1st CH\n",
  "Name" : "Fukusenshotei",
  "Total" : "",
  "Counter Hit" : "-2",
  "Property" : "SM,SM",
  "Damage" : "5,6",
  "Startup" : ""
}, {
  "Command" : "dbor d1, 2or FC 1, 2, 1+2",
  "Hit" : "+27",
  "Block" : "+16",
  "Notes" : "TC \nSuper Combo Gauge Cost 1\nBlock -2F/Hit +9F after Forcus Attack to canncel",
  "Name" : "Fukusenshotei to Focus Attack",
  "Total" : "",
  "Counter Hit" : "+27",
  "Property" : "SM,SM,SP",
  "Damage" : "5,6",
  "Startup" : ""
}, {
  "Command" : "dbor d2or FC 2",
  "Hit" : "+2",
  "Block" : "-9",
  "Notes" : "TC 4FC \n",
  "Name" : "Shotei",
  "Total" : "",
  "Counter Hit" : "+2",
  "Property" : "SM",
  "Damage" : "6",
  "Startup" : "12F"
}, {
  "Command" : "dbor d2or FC 2, 1+2",
  "Hit" : "+22",
  "Block" : "+11",
  "Notes" : "Super Combo Gauge Cost 1.\nBlock -7F/Hit +4F after Forcus Attack to canncel.",
  "Name" : "Shotei to Focus Attack",
  "Total" : "",
  "Counter Hit" : "+22",
  "Property" : "SM,SP",
  "Damage" : "6",
  "Startup" : ""
}, {
  "Command" : "dbor d3or FC 3",
  "Hit" : "-2",
  "Block" : "-11",
  "Notes" : "TC 6FC \nDamage() is when close hit\nEnable cancel by Special Move",
  "Name" : "Kurubushi Kick",
  "Total" : "43",
  "Counter Hit" : "-2",
  "Property" : "L",
  "Damage" : "7(10)",
  "Startup" : "15F"
}, {
  "Command" : "dbor d3or FC 3, 1+2",
  "Hit" : "+26",
  "Block" : "+17",
  "Notes" : "Super Combo Gauge Cost 1\nBlock -1F/Hit +8F after Forcus Attack to canncel",
  "Name" : "Kurubushi Kick to Focus Attack",
  "Total" : "",
  "Counter Hit" : "+26",
  "Property" : "L,SP",
  "Damage" : "7(10)",
  "Startup" : ""
}, {
  "Command" : "dbor d4or FC 4",
  "Hit" : "KDN",
  "Block" : "-27",
  "Notes" : "TC 6F\n",
  "Name" : "Ashibarai",
  "Total" : "",
  "Counter Hit" : "KDN",
  "Property" : "L",
  "Damage" : "20",
  "Startup" : "17F"
}, {
  "Command" : "b1",
  "Hit" : "KDN",
  "Block" : "-14",
  "Notes" : "C \n",
  "Name" : "Gaikaiken",
  "Total" : "46",
  "Counter Hit" : "KDN",
  "Property" : "H",
  "Damage" : "15",
  "Startup" : "14F"
}, {
  "Command" : "b1, 1+2",
  "Hit" : "KDN",
  "Block" : "+19",
  "Notes" : "Super Combo Gauge Cost 1\nBlock +1F after Forcus Attack to canncel",
  "Name" : "Gaikaiken to Focus Attack",
  "Total" : "",
  "Counter Hit" : "KDN",
  "Property" : "H,SP",
  "Damage" : "15",
  "Startup" : ""
}, {
  "Command" : "b2",
  "Hit" : "+8",
  "Block" : "-9",
  "Notes" : "H \n",
  "Name" : "Danretto",
  "Total" : "",
  "Counter Hit" : "KDN",
  "Property" : "M",
  "Damage" : "21",
  "Startup" : "23F"
}, {
  "Command" : "b4",
  "Hit" : "+1",
  "Block" : "-13",
  "Notes" : "",
  "Name" : "Taizankyaku",
  "Total" : "",
  "Counter Hit" : "+1",
  "Property" : "L",
  "Damage" : "15",
  "Startup" : "20F"
}, {
  "Command" : "ff2",
  "Hit" : "-2",
  "Block" : "-14",
  "Notes" : "",
  "Name" : "Shakunetsu Messho (1)",
  "Total" : "",
  "Counter Hit" : "-2",
  "Property" : "M",
  "Damage" : "14",
  "Startup" : "15F"
}, {
  "Command" : "ff2Ｊ 1",
  "Hit" : "KDN",
  "Block" : "-13",
  "Notes" : "WB \nCombo from 1st NH\nDisable 2nd after 1st whiff\n",
  "Name" : "Shakunetsu Messho",
  "Total" : "",
  "Counter Hit" : "KDN",
  "Property" : "M,M",
  "Damage" : "14,20",
  "Startup" : ""
}, {
  "Command" : "ff4",
  "Hit" : "+2C",
  "Block" : "±0",
  "Notes" : "Hit force to crouching\n",
  "Name" : "Ganretsuzan",
  "Total" : "49",
  "Counter Hit" : "+2C",
  "Property" : "M",
  "Damage" : "23",
  "Startup" : "20F"
}, {
  "Command" : "fff1",
  "Hit" : "KDN",
  "Block" : "+1",
  "Notes" : "",
  "Name" : "Shunjinkaida",
  "Total" : "",
  "Counter Hit" : "KDN",
  "Property" : "H",
  "Damage" : "30",
  "Startup" : "16F"
}, {
  "Command" : "fff3",
  "Hit" : "KDN",
  "Block" : "+4",
  "Notes" : "TJ 5F\nMeaty 5F in actualy",
  "Name" : "Tenmakuretsukyaku",
  "Total" : "",
  "Counter Hit" : "KDN",
  "Property" : "M",
  "Damage" : "30",
  "Startup" : "26F"
}, {
  "Command" : "Run more than three steps 4",
  "Hit" : "KDN",
  "Block" : "-24",
  "Notes" : "",
  "Name" : "Shunjingozan",
  "Total" : "",
  "Counter Hit" : "KDN",
  "Property" : "L",
  "Damage" : "23",
  "Startup" : "20F"
}, {
  "Command" : "WS 1",
  "Hit" : "+6",
  "Block" : "-5",
  "Notes" : "C \n",
  "Name" : "Hijiuchi",
  "Total" : "",
  "Counter Hit" : "+6",
  "Property" : "H",
  "Damage" : "12",
  "Startup" : "13F"
}, {
  "Command" : "WS 1, 1+2",
  "Hit" : "+27",
  "Block" : "+16",
  "Notes" : "Super Combo Gauge Cost 1\nBlock -2F/Hit +9F after Forcus Attack to canncel",
  "Name" : "Hijiuchi to Focus Attack",
  "Total" : "",
  "Counter Hit" : "+27",
  "Property" : "H,SP",
  "Damage" : "12",
  "Startup" : ""
}, {
  "Command" : "WS 2",
  "Hit" : "LNC",
  "Block" : "-15",
  "Notes" : "C \nEnable cancel by Special Move",
  "Name" : "Sotensho",
  "Total" : "49",
  "Counter Hit" : "LNC",
  "Property" : "M",
  "Damage" : "17",
  "Startup" : "15F"
}, {
  "Command" : "WS 2, 1+2",
  "Hit" : "LNC",
  "Block" : "+20",
  "Notes" : "Super Combo Gauge Cost 1\nBlock +2F after Forcus Attack to canncel",
  "Name" : "Sotensho to Focus Attack",
  "Total" : "",
  "Counter Hit" : "LNC",
  "Property" : "M,SP",
  "Damage" : "17",
  "Startup" : ""
}, {
  "Command" : "WS 3",
  "Hit" : "+2",
  "Block" : "-10",
  "Notes" : "C \n",
  "Name" : "Totsuhizageri",
  "Total" : "41",
  "Counter Hit" : "KDN",
  "Property" : "M",
  "Damage" : "17",
  "Startup" : "13F"
}, {
  "Command" : "WS 3",
  "Hit" : "+30",
  "Block" : "+18",
  "Notes" : "C ",
  "Name" : "Totsuhizageri",
  "Total" : "41",
  "Counter Hit" : "KDN",
  "Property" : "M,SP",
  "Damage" : "17",
  "Startup" : ""
}, {
  "Command" : "WS 4",
  "Hit" : "+2",
  "Block" : "-9",
  "Notes" : "",
  "Name" : "Toe Smash",
  "Total" : "",
  "Counter Hit" : "+2",
  "Property" : "M",
  "Damage" : "10",
  "Startup" : "11F"
}, {
  "Command" : "WS 4, 4",
  "Hit" : "-5C",
  "Block" : "-15",
  "Notes" : "Combo from 1st NH\nHit force to crouching",
  "Name" : "Shizan",
  "Total" : "",
  "Counter Hit" : "KDN",
  "Property" : "M,M",
  "Damage" : "10,20",
  "Startup" : ""
}, {
  "Command" : "During Vertical Jump 1",
  "Hit" : "-15",
  "Block" : "-25",
  "Notes" : "TJ 9F\nStart-up 16 to 43F in actualy\nBlock &amp; Hit values are in the fastest",
  "Name" : "Hijiotoshi",
  "Total" : "",
  "Counter Hit" : "-15",
  "Property" : "M",
  "Damage" : "10",
  "Startup" : "7F"
}, {
  "Command" : "During Vertical Jump 2",
  "Hit" : "-8",
  "Block" : "-18",
  "Notes" : "TJ 9F\nStart-up 18 to 43F in actualy\nBlock &amp; Hit values are in the fastest",
  "Name" : "Gokusengeki",
  "Total" : "",
  "Counter Hit" : "-8",
  "Property" : "M",
  "Damage" : "15",
  "Startup" : "9F"
}, {
  "Command" : "During Vertical Jump 3",
  "Hit" : "-15",
  "Block" : "-25",
  "Notes" : "TJ 9F\nStart-up 16 to 43F in actualy\nBlock &amp; Hit values are in the fastest",
  "Name" : "Maegeri",
  "Total" : "",
  "Counter Hit" : "-15",
  "Property" : "M",
  "Damage" : "10",
  "Startup" : "7F"
}, {
  "Command" : "During Vertical Jump 4",
  "Hit" : "-8",
  "Block" : "-18",
  "Notes" : "TJ 9F\nStart-up 18 to 43F in actualy\nBlock &amp; Hit values are in the fastest",
  "Name" : "Onikubigiri",
  "Total" : "",
  "Counter Hit" : "-8",
  "Property" : "M",
  "Damage" : "15",
  "Startup" : "9F"
}, {
  "Command" : "During Forward Jump 1",
  "Hit" : "-11",
  "Block" : "-22",
  "Notes" : "TJ 5F\nStart-up 14 to 38F in actualy\nBlock &amp; Hit values are in the fastest",
  "Name" : "Gokuken",
  "Total" : "",
  "Counter Hit" : "-11",
  "Property" : "M",
  "Damage" : "10",
  "Startup" : "9F"
}, {
  "Command" : "During Forward Jump 2",
  "Hit" : "-7",
  "Block" : "-17",
  "Notes" : "TJ 5F\nStart-up 14 to 37F in actualy\nBlock &amp; Hit values are in the fastest",
  "Name" : "Gokugeki",
  "Total" : "",
  "Counter Hit" : "-7",
  "Property" : "M",
  "Damage" : "15",
  "Startup" : "9F"
}, {
  "Command" : "During Forward Jump 3",
  "Hit" : "-16",
  "Block" : "-26",
  "Notes" : "TJ 5F\nStart-up 12 to 40F in actualy\nBlock &amp; Hit values are in the fastest",
  "Name" : "Rakusaishu",
  "Total" : "",
  "Counter Hit" : "-16",
  "Property" : "M",
  "Damage" : "10",
  "Startup" : "7F"
}, {
  "Command" : "During Forward Jump 4",
  "Hit" : "-9",
  "Block" : "-20",
  "Notes" : "TJ 5F\nStart-up 12 to 39F in actualy\nBlock &amp; Hit values are in the fastest",
  "Name" : "Tobisokuto",
  "Total" : "",
  "Counter Hit" : "-9",
  "Property" : "M",
  "Damage" : "15",
  "Startup" : "7F"
}, {
  "Command" : "Forward Jump peak d3",
  "Hit" : "+9C",
  "Block" : "±0",
  "Notes" : "Start-up frame is base values\nMeaty 6F in actualy\nNH force to crouching",
  "Name" : "Tenmakujinkyaku",
  "Total" : "",
  "Counter Hit" : "+9C",
  "Property" : "M",
  "Damage" : "14",
  "Startup" : "13F"
}, {
  "Command" : "1+2+3+4",
  "Hit" : "",
  "Block" : "",
  "Notes" : "To charging",
  "Name" : "Charging",
  "Total" : "55",
  "Counter Hit" : "",
  "Property" : "SP",
  "Damage" : "-",
  "Startup" : ""
}, {
  "Command" : "BT 1or 2",
  "Hit" : "+8",
  "Block" : "+1",
  "Notes" : "Equivalent to Sengeki (<img src=\"../lp.bmp\" class=\"c\">), can't connect Kimon Rendan (<img src=\"../lp.bmp\" class=\"c\"><img src=\"../c.bmp\" class=\"c\"><img src=\"../lp.bmp\" class=\"c\">)",
  "Name" : "Sengeki",
  "Total" : "",
  "Counter Hit" : "+8",
  "Property" : "H",
  "Damage" : "7",
  "Startup" : "10F"
}, {
  "Command" : "BT 4or 3",
  "Hit" : "+2",
  "Block" : "-13",
  "Notes" : "Equivalent to High Kick (<img src=\"../rk.bmp\" class=\"c\">)",
  "Name" : "High Kick",
  "Total" : "",
  "Counter Hit" : "+2",
  "Property" : "H",
  "Damage" : "12",
  "Startup" : "14F"
}, {
  "Command" : "BT d1or d2",
  "Hit" : "+7",
  "Block" : "-4",
  "Notes" : "Equivalent to Shotei (<img src=\"../2.bmp\" class=\"c\"><img src=\"../rp.bmp\" class=\"c\">)",
  "Name" : "Shotei",
  "Total" : "",
  "Counter Hit" : "+7",
  "Property" : "SM",
  "Damage" : "6",
  "Startup" : "12F"
}, {
  "Command" : "BT d3or d4",
  "Hit" : "KDN",
  "Block" : "-27",
  "Notes" : "Equivalent to Ashibarai (<img src=\"../2.bmp\" class=\"c\"><img src=\"../rk.bmp\" class=\"c\">)\n",
  "Name" : "Ashibarai",
  "Total" : "",
  "Counter Hit" : "KDN",
  "Property" : "L",
  "Damage" : "17",
  "Startup" : "17F"
}, {
  "Command" : "1+2",
  "Hit" : "-8",
  "Block" : "-20",
  "Notes" : "PC 8F\nHold no more than 20F\nInput<img src=\"../4.bmp\" class=\"c\"><img src=\"../4.bmp\" class=\"c\">or<img src=\"../6.bmp\" class=\"c\"><img src=\"../6.bmp\" class=\"c\">to cancel\nEnable recovery after some paticular moves for the cost 1 guage",
  "Name" : "Focus Attack Lv.1",
  "Total" : "",
  "Counter Hit" : "-8",
  "Property" : "H",
  "Damage" : "14",
  "Startup" : "31F"
}, {
  "Command" : "1+2Hold ff",
  "Hit" : "",
  "Block" : "",
  "Notes" : "PC 8F\nRecovery 15F after input<img src=\"../6.bmp\" class=\"c\"><img src=\"../6.bmp\" class=\"c\">",
  "Name" : "Focus Attack to Cancel",
  "Total" : "15",
  "Counter Hit" : "",
  "Property" : "SP",
  "Damage" : "-",
  "Startup" : ""
}, {
  "Command" : "1+2Hold bb",
  "Hit" : "",
  "Block" : "",
  "Notes" : "PC 8F\nRecovery 25F after input<img src=\"../4.bmp\" class=\"c\"><img src=\"../4.bmp\" class=\"c\">",
  "Name" : "Focus Attack to Cancel Back Dash",
  "Total" : "25",
  "Counter Hit" : "",
  "Property" : "SP",
  "Damage" : "-",
  "Startup" : ""
}, {
  "Command" : "1+2ff",
  "Hit" : "+7",
  "Block" : "-5",
  "Notes" : "PC 8F",
  "Name" : "Focus Attack Lv.1 to Cancel",
  "Total" : "",
  "Counter Hit" : "+7",
  "Property" : "H,SP",
  "Damage" : "14",
  "Startup" : ""
}, {
  "Command" : "1+2Hold ",
  "Hit" : "KDN",
  "Block" : "-11",
  "Notes" : "PC 8F\nStart-up frame is to hold 21 to 25F\nStart-up 11 + hold frame over 26F",
  "Name" : "Focus Attack Lv.2",
  "Total" : "",
  "Counter Hit" : "KDN",
  "Property" : "H",
  "Damage" : "20",
  "Startup" : "36F"
}, {
  "Command" : "1+2Hold ff",
  "Hit" : "KDN",
  "Block" : "+4",
  "Notes" : "PC 8F",
  "Name" : "Focus Attack Lv.2 to Cancel",
  "Total" : "",
  "Counter Hit" : "KDN",
  "Property" : "H,SP",
  "Damage" : "20",
  "Startup" : ""
}, {
  "Command" : "1+2Hold (Max) ",
  "Hit" : "KDN",
  "Block" : "KDN",
  "Notes" : "PC 8F",
  "Name" : "Focus Attack Lv.3",
  "Total" : "",
  "Counter Hit" : "KDN",
  "Property" : "UB(H)",
  "Damage" : "25",
  "Startup" : "65F"
}, {
  "Command" : "1+2Hold (Max) ff",
  "Hit" : "KDN",
  "Block" : "KDN",
  "Notes" : "PC 8F",
  "Name" : "Focus Attack Lv.3 to Cancel",
  "Total" : "",
  "Counter Hit" : "KDN",
  "Property" : "UB(H),SP",
  "Damage" : "25",
  "Startup" : ""
}, {
  "Command" : "ddff1",
  "Hit" : "-6",
  "Block" : "-14",
  "Notes" : "Frame values are in the case of close to\n",
  "Name" : "Gohadoken (Low)",
  "Total" : "56",
  "Counter Hit" : "-6",
  "Property" : "SM",
  "Damage" : "12",
  "Startup" : "19F"
}, {
  "Command" : "ddff1, 1+2",
  "Hit" : "+32",
  "Block" : "+24",
  "Notes" : "Super Combo Gauge Cost 1.\nBlock +7F/Hit +15F after Forcus Attack to canncel.",
  "Name" : "Gohadoken (Low) to Focus Attack",
  "Total" : "",
  "Counter Hit" : "+32",
  "Property" : "SM,SP",
  "Damage" : "12",
  "Startup" : ""
}, {
  "Command" : "ddff2",
  "Hit" : "-6",
  "Block" : "-14",
  "Notes" : "Frame values are in the case of close to\n",
  "Name" : "Gohadoken (High)",
  "Total" : "56",
  "Counter Hit" : "-6",
  "Property" : "SM",
  "Damage" : "12",
  "Startup" : "19F"
}, {
  "Command" : "ddff2, 1+2",
  "Hit" : "+32",
  "Block" : "+24",
  "Notes" : "Super Combo Gauge Cost 1.\nBlock +7F/Hit +15F after Forcus Attack to canncel.",
  "Name" : "Gohadoken (High) to Focus Attack",
  "Total" : "",
  "Counter Hit" : "+32",
  "Property" : "SM,SP",
  "Damage" : "12",
  "Startup" : ""
}, {
  "Command" : "fdfddbb1",
  "Hit" : "-4",
  "Block" : "-12",
  "Notes" : "Easy command<img src=\"../6.bmp\" class=\"c\"><img src=\"../2.bmp\" class=\"c\"><img src=\"../4.bmp\" class=\"c\"><img src=\"../lp.bmp\" class=\"c\">\nFrame values are in the case of close to\n",
  "Name" : "Shakunetsu Hadoken (Low)",
  "Total" : "64",
  "Counter Hit" : "-4",
  "Property" : "SM",
  "Damage" : "13",
  "Startup" : "28F"
}, {
  "Command" : "fdfddbb1, 1+2",
  "Hit" : "+33",
  "Block" : "+25",
  "Notes" : "Super Combo Gauge Cost 1\nBlock +8F after Forcus Attack to canncel",
  "Name" : "Shakunetsu Hadoken (Low) to Focus Attack",
  "Total" : "",
  "Counter Hit" : "+33",
  "Property" : "SM,SP",
  "Damage" : "13",
  "Startup" : ""
}, {
  "Command" : "fdfddbb2",
  "Hit" : "KDN",
  "Block" : "-1",
  "Notes" : "Easy command<img src=\"../6.bmp\" class=\"c\"><img src=\"../2.bmp\" class=\"c\"><img src=\"../4.bmp\" class=\"c\"><img src=\"../rp.bmp\" class=\"c\">\nFrame values are in the case of close to",
  "Name" : "Shakunetsu Hadoken (High)",
  "Total" : "74",
  "Counter Hit" : "KDN",
  "Property" : "SM*3",
  "Damage" : "9*3",
  "Startup" : "33F"
}, {
  "Command" : "fdfddbb2, 1+2",
  "Hit" : "KDN",
  "Block" : "+41G",
  "Notes" : "Super Combo Gauge Cost 1\nBlock +24<sup>G</sup>F after Forcus Attack to canncel",
  "Name" : "Shakunetsu Hadoken (High) to Focus Attack",
  "Total" : "",
  "Counter Hit" : "KDN",
  "Property" : "SM*3,SP",
  "Damage" : "9*3",
  "Startup" : ""
}, {
  "Command" : "fddf1",
  "Hit" : "LNC",
  "Block" : "-25",
  "Notes" : "TC 6F",
  "Name" : "Goshoryuken (Low)",
  "Total" : "",
  "Counter Hit" : "LNC",
  "Property" : "SM",
  "Damage" : "15",
  "Startup" : "10F"
}, {
  "Command" : "fddf1, 1+2",
  "Hit" : "LNC",
  "Block" : "+21",
  "Notes" : "TC 6F\nSuper Combo Gauge Cost 1\nBlock +3F after Forcus Attack to canncel",
  "Name" : "Goshoryuken (Low) to Focus Attack",
  "Total" : "",
  "Counter Hit" : "LNC",
  "Property" : "SM,SP",
  "Damage" : "15",
  "Startup" : ""
}, {
  "Command" : "fddf2",
  "Hit" : "LNC",
  "Block" : "-34",
  "Notes" : "TC 6F\nInvinciblity 8F",
  "Name" : "Goshoryuken (High)",
  "Total" : "",
  "Counter Hit" : "LNC",
  "Property" : "SM*3",
  "Damage" : "6,6,20",
  "Startup" : "11F"
}, {
  "Command" : "fddf2, 1+2",
  "Hit" : "+32",
  "Block" : "+19",
  "Notes" : "TC 6F\nSuper Combo Gauge Cost 1\nBlock +1F/Hit +14F after Forcus Attack to canncel",
  "Name" : "Goshoryuken (High) to Focus Attack",
  "Total" : "",
  "Counter Hit" : "+32",
  "Property" : "SM,SP",
  "Damage" : "6",
  "Startup" : ""
}, {
  "Command" : "fddf2, 1+2",
  "Hit" : "LNC",
  "Block" : "+21",
  "Notes" : "TC 6F\nSuper Combo Gauge Cost 1\nBlock +3F after Forcus Attack to canncel",
  "Name" : "Goshoryuken (High,2nd) to Focus Attack",
  "Total" : "",
  "Counter Hit" : "LNC",
  "Property" : "SM*2,SP",
  "Damage" : "6,6",
  "Startup" : ""
}, {
  "Command" : "fddf3or 4",
  "Hit" : "",
  "Block" : "",
  "Notes" : "TJ 5F\nMoving distance<img src=\"../lk.bmp\" class=\"c\">&lt;<img src=\"../rk.bmp\" class=\"c\">",
  "Name" : "Hyakkishu",
  "Total" : "",
  "Counter Hit" : "",
  "Property" : "SP",
  "Damage" : "-",
  "Startup" : ""
}, {
  "Command" : "During Hyakkishu ☆ ",
  "Hit" : "KDN",
  "Block" : "-24",
  "Notes" : "",
  "Name" : "Hyakkigoshozan",
  "Total" : "94",
  "Counter Hit" : "KDN",
  "Property" : "L",
  "Damage" : "23",
  "Startup" : "51F"
}, {
  "Command" : "During Hyakkishu 1",
  "Hit" : "KDN",
  "Block" : "-1",
  "Notes" : "Fastest start-up 37F in actualy\n",
  "Name" : "Hyakkigosho",
  "Total" : "",
  "Counter Hit" : "KDN",
  "Property" : "H",
  "Damage" : "15",
  "Startup" : "7F"
}, {
  "Command" : "During Hyakkishu 2",
  "Hit" : "KDN",
  "Block" : "-9C",
  "Notes" : "Fastest start-up 43F in actualy\n",
  "Name" : "Hyakkigohasatsu",
  "Total" : "",
  "Counter Hit" : "KDN",
  "Property" : "M",
  "Damage" : "20",
  "Startup" : "16F"
}, {
  "Command" : "During Hyakkishu 3",
  "Hit" : "+24Sp",
  "Block" : "-9",
  "Notes" : "H TS \nFastest start-up 42F in actualy\n",
  "Name" : "Hyakkigosen",
  "Total" : "",
  "Counter Hit" : "KDN",
  "Property" : "M",
  "Damage" : "21",
  "Startup" : "14F"
}, {
  "Command" : "During Hyakkishu 4",
  "Hit" : "+16C",
  "Block" : "+4G",
  "Notes" : "Hit force to crouching\nMeaty 5F in actualy\nFastest start-up 44F in actualy\n",
  "Name" : "Hyakkigojin",
  "Total" : "",
  "Counter Hit" : "+16C",
  "Property" : "SM",
  "Damage" : "15",
  "Startup" : "14F"
}, {
  "Command" : "ddbb3",
  "Hit" : "KDN",
  "Block" : "-15",
  "Notes" : "TJ 9F",
  "Name" : "Tatsumaki Zankukyaku (Low)",
  "Total" : "",
  "Counter Hit" : "KDN",
  "Property" : "H",
  "Damage" : "10",
  "Startup" : "15F"
}, {
  "Command" : "ddbb4",
  "Hit" : "KDN",
  "Block" : "-15",
  "Notes" : "",
  "Name" : "Tatsumaki Zankukyaku (High)",
  "Total" : "",
  "Counter Hit" : "KDN",
  "Property" : "SM,H*3",
  "Damage" : "13,6,6,6",
  "Startup" : "10F"
}, {
  "Command" : "During Jump ddff1or 2",
  "Hit" : "+4",
  "Block" : "-7",
  "Notes" : "Frame values are just before landing",
  "Name" : "Zanku Hadoken",
  "Total" : "",
  "Counter Hit" : "+4",
  "Property" : "SM",
  "Damage" : "10",
  "Startup" : "17F"
}, {
  "Command" : "During Jump ddbb3or 4",
  "Hit" : "KDN",
  "Block" : "+2",
  "Notes" : "Frame values are just before landing",
  "Name" : "AirBorne Tatsumaki Zankukyaku",
  "Total" : "",
  "Counter Hit" : "KDN",
  "Property" : "SM",
  "Damage" : "10",
  "Startup" : "13F"
}, {
  "Command" : "fddf3+4",
  "Hit" : "",
  "Block" : "",
  "Notes" : "Invinciblity 5F",
  "Name" : "Ashura Senku",
  "Total" : "70",
  "Counter Hit" : "",
  "Property" : "SP",
  "Damage" : "-",
  "Startup" : ""
}, {
  "Command" : "bddb3+4",
  "Hit" : "",
  "Block" : "",
  "Notes" : "Invinciblity 5F",
  "Name" : "Ashura Senku (Back)",
  "Total" : "75",
  "Counter Hit" : "",
  "Property" : "SP",
  "Damage" : "-",
  "Startup" : ""
}, {
  "Command" : "ddff1+2",
  "Hit" : "KDN",
  "Block" : "+1",
  "Notes" : "Super Combo Gauge Cost 1\nFrame values are in the case of close to",
  "Name" : "EX Gohadoken",
  "Total" : "",
  "Counter Hit" : "KDN",
  "Property" : "SM,SM",
  "Damage" : "10,10",
  "Startup" : "19F"
}, {
  "Command" : "fdfddbb1+2",
  "Hit" : "KDN",
  "Block" : "+9",
  "Notes" : "Super Combo Gauge Cost 1\nFrame values are in the case of close to",
  "Name" : "EX Shakunetsu Hadoken",
  "Total" : "",
  "Counter Hit" : "KDN",
  "Property" : "SM*3",
  "Damage" : "12*3",
  "Startup" : "28F"
}, {
  "Command" : "fddf1+2",
  "Hit" : "LNC",
  "Block" : "-34",
  "Notes" : "Super Combo Gauge Cost 1\nInvinciblity 1F",
  "Name" : "EX Goshoryuken",
  "Total" : "",
  "Counter Hit" : "-",
  "Property" : "SM*3",
  "Damage" : "6,6,20",
  "Startup" : "11F"
}, {
  "Command" : "During CH fddf1+2",
  "Hit" : "",
  "Block" : "",
  "Notes" : "Super Combo Gauge Cost 1",
  "Name" : "Messatsu Goshoryu",
  "Total" : "",
  "Counter Hit" : "KDN",
  "Property" : "SM,Th",
  "Damage" : "7,8,9*3",
  "Startup" : ""
}, {
  "Command" : "ddbb3+4",
  "Hit" : "KDN",
  "Block" : "-22",
  "Notes" : "TS \nSuper Combo Gauge Cost 1\n",
  "Name" : "EX Tatsumaki Zankukyaku",
  "Total" : "",
  "Counter Hit" : "KDN",
  "Property" : "SM*4",
  "Damage" : "6,6,6,20",
  "Startup" : "10F"
}, {
  "Command" : "During Jump ddff1+2",
  "Hit" : "+39",
  "Block" : "+20G",
  "Notes" : "Super Combo Gauge Cost 1",
  "Name" : "EX Zanku Hadoken",
  "Total" : "",
  "Counter Hit" : "+39",
  "Property" : "SM,SM",
  "Damage" : "10,10",
  "Startup" : "8F"
}, {
  "Command" : "During Jump ddbb3+4",
  "Hit" : "KDN",
  "Block" : "+9",
  "Notes" : "Super Combo Gauge Cost 1",
  "Name" : "EX AirBorne Tatsumaki Zankukyaku",
  "Total" : "",
  "Counter Hit" : "KDN",
  "Property" : "SM",
  "Damage" : "10,10",
  "Startup" : "13F"
}, {
  "Command" : "f3+4ddff1+2",
  "Hit" : "+20",
  "Block" : "+15G",
  "Notes" : "Super Combo Gauge Cost 1\nCombo from 1st NH\nCan be delayed 7F",
  "Name" : "Hisenkyaku to EX Zanku Hadoken",
  "Total" : "",
  "Counter Hit" : "+20",
  "Property" : "M,SM*2",
  "Damage" : "20,10,10",
  "Startup" : "22F"
}, {
  "Command" : "f3+4ddbb3+4",
  "Hit" : "KDN",
  "Block" : "-35",
  "Notes" : "TS \nSuper Combo Gauge Cost 1\nCombo from 1st NH\nCan be delayed 7F",
  "Name" : "Hisenkyaku to EX AirBorne Tatsumaki Zankukyaku",
  "Total" : "",
  "Counter Hit" : "KDN",
  "Property" : "M,SM*3",
  "Damage" : "20,6,6,20",
  "Startup" : "22F"
}, {
  "Command" : "ddffddff1+2",
  "Hit" : "KDN",
  "Block" : "+2",
  "Notes" : "Super Combo Gauge Cost 2",
  "Name" : "Messatsu Gohado",
  "Total" : "",
  "Counter Hit" : "KDN",
  "Property" : "SM*5",
  "Damage" : "20*5",
  "Startup" : "9F"
}, {
  "Command" : "During Rage 1, 1bor f3, 2",
  "Hit" : "KDN",
  "Block" : "KDN",
  "Notes" : "Another command<img src=\"../lp.bmp\" class=\"c\"><img src=\"../c.bmp\" class=\"c\"><img src=\"../lp.bmp\" class=\"c\"><img src=\"../4.bmp\" class=\"c\">or<img src=\"../6.bmp\" class=\"c\"><img src=\"../rpk.bmp\" class=\"c\">\nGuard Point 8F\nEnable evade input<img src=\"../8'.bmp\" class=\"c\">\n",
  "Name" : "Wrath of the Raging Demon",
  "Total" : "",
  "Counter Hit" : "KDN",
  "Property" : "Th(M)",
  "Damage" : "55",
  "Startup" : "16F"
} ]